python_unsiotools-1.0.1.dist-info/RECORD
python_unsiotools-1.0.1.dist-info/entry_points.txt
python_unsiotools-1.0.1.dist-info/WHEEL
python_unsiotools-1.0.1.dist-info/top_level.txt
python_unsiotools-1.0.1.dist-info/METADATA
python_unsiotools-1.0.1.dist-info/LICENSE
unsiotools/version.py
unsiotools/py_unstools.py
unsiotools/_py_unstools.cpython-36m-x86_64-linux-gnu.so
unsiotools/__init__.py
unsiotools/uns_simu.py
unsiotools/general/ctools.py
unsiotools/general/__init__.py
unsiotools/simulations/cfalcon.py
unsiotools/simulations/ccod.py
unsiotools/simulations/corbits.py
unsiotools/simulations/ctestunsio.py
unsiotools/simulations/ccom.py
unsiotools/simulations/cmovie.py
unsiotools/simulations/cuns_analysis.py
unsiotools/simulations/cinert.py
unsiotools/simulations/c2dpgplot.py
unsiotools/simulations/csnapshot.py
unsiotools/simulations/crectify.py
unsiotools/simulations/cramses2gadget.py
unsiotools/simulations/__init__.py
unsiotools/simulations/ctree.py
unsiotools/simulations/c2dplot.py
unsiotools/simulations/creducesim.py
unsiotools/simulations/cplotinert.py
python_unsiotools.libs/libWDutils-9c8a2cc6.so
python_unsiotools.libs/libunsio-04812e3a.so
python_unsiotools.libs/libJCLprojects-c9a3109a.so
python_unsiotools.libs/libsqlite3-87a23cdb.so.0.8.6
python_unsiotools.libs/libgfortran-2e0d59d6.so.5.0.0
python_unsiotools.libs/libhdf5-59624cfe.so.6.0.4
python_unsiotools.libs/libpgplot-55184b35.so
python_unsiotools.libs/libJCLutils-213fc727.so
python_unsiotools.libs/libquadmath-2d0c479f.so.0.0.0
python_unsiotools.libs/libhdf5_cpp-9a3db22a.so.6.0.4
python_unsiotools.libs/libfalcON-efbd1218.so
python_unsiotools-1.0.1.data/scripts/uns_2dplot.py
python_unsiotools-1.0.1.data/scripts/test_cfalcon.py
python_unsiotools-1.0.1.data/scripts/age_to_density.py
python_unsiotools-1.0.1.data/scripts/uns_extract_halo.py
