Metadata-Version: 2.1
Name: python-unsiotools
Version: 1.0.1
Summary: Python wrapper to unsiotools
Home-page: https://projets.lam.fr/projects/uns_projects
Author: Jean-Charles LAMBERT
Author-email: jean-charles.lambert@lam.fr
License: CeCILL2.1 (https://opensource.org/licenses/CECILL-2.1)
Platform: Linux
Platform: Mac OS-X
Platform: Unix
Classifier: Intended Audience :: Developers
Classifier: Intended Audience :: Science/Research
Classifier: Programming Language :: C
Classifier: Programming Language :: C++
Classifier: Programming Language :: Python
Classifier: Programming Language :: Python :: 2.7
Classifier: Programming Language :: Python :: 3.4
Classifier: Programming Language :: Python :: 3.5
Classifier: Programming Language :: Python :: 3.6
Classifier: Programming Language :: Python :: 3.7
Classifier: Programming Language :: Python :: 3.8
Classifier: Programming Language :: Python :: 3.9
Classifier: Programming Language :: Python :: 3.10
Classifier: Programming Language :: Python :: 3.11
Classifier: Topic :: Scientific/Engineering :: Astronomy
Classifier: Topic :: Software Development
Requires-Python: >=2.7,!=3.0.*,!=3.1.*,!=3.2.*,!=3.3.*
License-File: LICENSE
Requires-Dist: python-unsio
Requires-Dist: numpy
